nordpool/__init__.py
nordpool/nordpool.py
nordpool_daily_averages-1.1.42.dist-info/LICENSE
nordpool_daily_averages-1.1.42.dist-info/METADATA
nordpool_daily_averages-1.1.42.dist-info/WHEEL
nordpool_daily_averages-1.1.42.dist-info/top_level.txt
nordpool_daily_averages-1.1.42.dist-info/RECORD
