Metadata-Version: 2.1
Name: nordpool-daily-averages
Version: 1.1.42
Summary: REST api wrapper for nordpool average daily spot prices
Author-email: Gunnar Svanberg <gus.svanberg@gmail.com>
License: MIT License
Project-URL: Source, https://github.com/g-svanberg/nordpool-imd-daily-average
Project-URL: Documentation, https://github.com/g-svanberg/nordpool-imd-daily-average/blob/main/README.md
Classifier: Programming Language :: Python :: 3
Classifier: License :: OSI Approved :: MIT License
Classifier: Operating System :: OS Independent
Classifier: Development Status :: 4 - Beta
Classifier: Intended Audience :: Developers
Classifier: Intended Audience :: Information Technology
Classifier: Intended Audience :: System Administrators
Classifier: Topic :: Software Development :: Libraries
Requires-Python: >=3.9
License-File: LICENSE
Requires-Dist: httpx
Requires-Dist: pytz
